{
  "generator-jhipster": {
    "promptValues": {
      "packageName": "com.contrader.tomatorulesmicroservices"
    },
    "jhipsterVersion": "5.2.1",
    "applicationType": "microservice",
    "baseName": "entities",
    "packageName": "com.contrader.tomatorulesmicroservices",
    "packageFolder": "com/contrader/tomatorulesmicroservices",
    "serverPort": "8081",
    "authenticationType": "jwt",
    "cacheProvider": "hazelcast",
    "enableHibernateCache": false,
    "websocket": false,
    "databaseType": "sql",
    "devDatabaseType": "h2Disk",
    "prodDatabaseType": "mysql",
    "searchEngine": false,
    "messageBroker": false,
    "serviceDiscoveryType": "consul",
    "buildTool": "maven",
    "enableSwaggerCodegen": false,
    "jwtSecretKey": "465c8dc05b605a2172835266b97dd375ae0e2ecd",
    "enableTranslation": false,
    "testFrameworks": [],
    "jhiPrefix": "jhi",
    "clientPackageManager": "npm",
    "skipClient": true,
    "skipUserManagement": true
  }
}